{
  "template": "HR",
  "total_rows": 10,
  "error_rows": 4,
  "error_pct": 40.0,
  "critical": 9,
  "warnings": 3,
  "status": "fail",
  "generated_at": "2026-04-23T17:04:10.070126",
  "errors": [
    {
      "row_id": 0,
      "column_name": "Employee Code",
      "error_type": "MISSING_COLUMN",
      "severity": "critical",
      "message": "Cột 'Employee Code' không tồn tại trong file.",
      "rule_id": "sys_missing_col"
    },
    {
      "row_id": 3,
      "column_name": "Employee Full Name",
      "error_type": "NULL_REQUIRED",
      "severity": "critical",
      "message": "Cột 'Employee Full Name' bắt buộc nhưng đang trống.",
      "rule_id": "sys_null_required"
    },
    {
      "row_id": 7,
      "column_name": "Employee Full Name",
      "error_type": "NULL_REQUIRED",
      "severity": "critical",
      "message": "Cột 'Employee Full Name' bắt buộc nhưng đang trống.",
      "rule_id": "sys_null_required"
    },
    {
      "row_id": 11,
      "column_name": "Employee Full Name",
      "error_type": "NULL_REQUIRED",
      "severity": "critical",
      "message": "Cột 'Employee Full Name' bắt buộc nhưng đang trống.",
      "rule_id": "sys_null_required"
    },
    {
      "row_id": 0,
      "column_name": "Employee Full Name",
      "error_type": "NULL_EXCEEDED",
      "severity": "warning",
      "message": "Cột 'Employee Full Name' có 30.0% null (cho phép 0%).",
      "rule_id": "sys_null_pct"
    },
    {
      "row_id": 3,
      "column_name": "Gender",
      "error_type": "NULL_REQUIRED",
      "severity": "critical",
      "message": "Cột 'Gender' bắt buộc nhưng đang trống.",
      "rule_id": "sys_null_required"
    },
    {
      "row_id": 11,
      "column_name": "Gender",
      "error_type": "NULL_REQUIRED",
      "severity": "critical",
      "message": "Cột 'Gender' bắt buộc nhưng đang trống.",
      "rule_id": "sys_null_required"
    },
    {
      "row_id": 0,
      "column_name": "Gender",
      "error_type": "NULL_EXCEEDED",
      "severity": "warning",
      "message": "Cột 'Gender' có 20.0% null (cho phép 0%).",
      "rule_id": "sys_null_pct"
    },
    {
      "row_id": 5,
      "column_name": "Phone Number",
      "error_type": "NULL_REQUIRED",
      "severity": "critical",
      "message": "Cột 'Phone Number' bắt buộc nhưng đang trống.",
      "rule_id": "sys_null_required"
    },
    {
      "row_id": 11,
      "column_name": "Phone Number",
      "error_type": "NULL_REQUIRED",
      "severity": "critical",
      "message": "Cột 'Phone Number' bắt buộc nhưng đang trống.",
      "rule_id": "sys_null_required"
    },
    {
      "row_id": 0,
      "column_name": "Phone Number",
      "error_type": "NULL_EXCEEDED",
      "severity": "warning",
      "message": "Cột 'Phone Number' có 20.0% null (cho phép 0%).",
      "rule_id": "sys_null_pct"
    },
    {
      "row_id": 0,
      "column_name": "employee code",
      "error_type": "MISSING_COLUMN",
      "severity": "critical",
      "message": "Rule 'hr_r1': cột 'employee code' không tồn tại.",
      "rule_id": "hr_r1"
    }
  ]
}